[{"name":"Abomasnow","gender":"M","item":"Leftovers","evs":{"hp":188,"atk":252,"spd":68},"moves":["Ice Shard","Leech Seed","Protect","Wood Hammer"]},{"name":"Tentacruel","gender":"M","item":"Black Sludge","evs":{"hp":204,"def":208,"spd":96},"moves":["Toxic Spikes","Scald","Rapid Spin","Blizzard"]},{"name":"Heatran","gender":"M","item":"Leftovers","evs":{"hp":248,"spd":252,"spe":8},"moves":["Stealth Rock","Lava Plume","Earth Power","Roar"]},{"name":"Kyurem","item":"Leftovers","evs":{"hp":56,"spa":236,"spd":216},"moves":["Substitute","Dragon Pulse","Blizzard","Focus Blast"]},{"name":"Reuniclus","gender":"F","item":"Life Orb","evs":{"hp":248,"def":252,"spd":8},"moves":["Calm Mind","Focus Blast","Psyshock","Recover"]},{"name":"Conkeldurr","gender":"M","item":"Leftovers","evs":{"hp":196,"atk":120,"spd":188,"spe":4},"moves":["Bulk Up","Drain Punch","Mach Punch","Payback"]}]